wheke/__init__.py
wheke/__main__.py
wheke/_cli.py
wheke/_constants.py
wheke/_core.py
wheke/_demo.py
wheke/_pod.py
wheke/_service.py
wheke/_settings.py
wheke/py.typed
wheke-0.7.0.dist-info/licenses/LICENSE.txt
wheke-0.7.0.dist-info/METADATA
wheke-0.7.0.dist-info/WHEEL
wheke-0.7.0.dist-info/entry_points.txt
wheke-0.7.0.dist-info/top_level.txt
wheke-0.7.0.dist-info/RECORD
