Metadata-Version: 2.4
Name: wheke
Version: 0.7.0
Summary: A cute framework for small self-hosted apps
Author-email: Humberto Rocha <humrochagf@gmail.com>
License-Expression: MIT
Project-URL: Documentation, https://wheke.humberto.io/
Project-URL: Issues, https://github.com/humrochagf/wheke/issues
Project-URL: Source, https://github.com/humrochagf/wheke
Classifier: Development Status :: 4 - Beta
Classifier: Framework :: FastAPI
Classifier: Programming Language :: Python :: 3.12
Classifier: Programming Language :: Python :: 3.13
Classifier: Programming Language :: Python :: 3.14
Classifier: Programming Language :: Python :: Implementation :: CPython
Classifier: Programming Language :: Python :: Implementation :: PyPy
Classifier: Programming Language :: Python
Classifier: Topic :: Internet :: WWW/HTTP :: HTTP Servers
Classifier: Topic :: Internet :: WWW/HTTP
Classifier: Topic :: Internet
Requires-Python: >=3.12
License-File: LICENSE.txt
Requires-Dist: anyio
Requires-Dist: fastapi
Requires-Dist: pydantic
Requires-Dist: pydantic-settings
Requires-Dist: rich
Requires-Dist: svcs
Requires-Dist: typer
Dynamic: license-file
